{
  "script": "a11y07",
  "batch": "a11yOrgsMore",
  "what": "Axe, IBM, WAVE, and 16 custom tests",
  "strict": true,
  "testDate": "2021-12-07",
  "timeStamp": "14r78",
  "logCount": 53,
  "logSize": 3330,
  "prohibitedCount": 0,
  "visitTimeoutCount": 0,
  "visitRejectionCount": 0,
  "presses": 0,
  "amountRead": 0,
  "acts": [
    {
      "type": "launch",
      "which": "webkit",
      "what": "used for tests on which chromium fails on some URLs"
    },
    {
      "type": "url",
      "which": "https://mk-sense.com/",
      "what": "Make-Sense",
      "result": "https://mk-sense.com/"
    },
    {
      "type": "test",
      "which": "motion",
      "what": "motion",
      "delay": 2400,
      "interval": 2600,
      "count": 5,
      "url": "https://mk-sense.com/",
      "result": {
        "bytes": [
          520267,
          522532,
          524268,
          524268,
          524268
        ],
        "localRatios": [
          1.004,
          1.003,
          1,
          1
        ],
        "meanLocalRatio": 1.002,
        "maxLocalRatio": 1.004,
        "globalRatio": 1.008,
        "pixelChanges": [
          332,
          435464,
          0,
          0
        ],
        "meanPixelChange": 108949,
        "maxPixelChange": 435464,
        "changeFrequency": 0.5
      }
    },
    {
      "type": "test",
      "which": "axe",
      "withItems": true,
      "rules": [],
      "what": "Axe",
      "url": "https://mk-sense.com/",
      "result": {
        "warnings": 0,
        "violations": {
          "minor": 0,
          "moderate": 3,
          "serious": 5,
          "critical": 1
        },
        "items": [
          {
            "rule": "aria-allowed-attr",
            "description": "Ensures ARIA attributes are allowed for an element's role",
            "impact": "critical",
            "elements": [
              {
                "selector": "iframe[width=\"\\35 60\"]",
                "impact": "critical",
                "must pass all of": [
                  {
                    "check": "aria-prohibited-attr",
                    "description": "ARIA attribute cannot be used: aria-label",
                    "impact": "critical"
                  }
                ]
              }
            ]
          },
          {
            "rule": "color-contrast",
            "description": "Ensures the contrast between foreground and background colors meets WCAG 2 AA contrast ratio thresholds",
            "impact": "serious",
            "elements": [
              {
                "selector": "#hs-eu-confirmation-button",
                "impact": "serious",
                "must pass any of": [
                  {
                    "check": "color-contrast",
                    "description": "Element has insufficient color contrast of 3.08 (foreground color: #ffffff, background color: #4a99d4, font size: 9.0pt (12px), font weight: normal). Expected contrast ratio of 4.5:1",
                    "impact": "serious"
                  }
                ]
              }
            ]
          },
          {
            "rule": "landmark-no-duplicate-banner",
            "description": "Ensures the document has at most one banner landmark",
            "impact": "moderate",
            "elements": [
              {
                "selector": "#hs-eu-cookie-confirmation",
                "impact": "moderate",
                "must pass any of": [
                  {
                    "check": "page-no-duplicate-banner",
                    "description": "Document has more than one banner landmark",
                    "impact": "moderate"
                  }
                ]
              }
            ]
          },
          {
            "rule": "landmark-unique",
            "description": "Landmarks should have a unique role or role/label/title (i.e. accessible name) combination",
            "impact": "moderate",
            "elements": [
              {
                "selector": "#hs-eu-cookie-confirmation",
                "impact": "moderate",
                "must pass any of": [
                  {
                    "check": "landmark-is-unique",
                    "description": "The landmark must have a unique aria-label, aria-labelledby, or title to make landmarks distinguishable",
                    "impact": "moderate"
                  }
                ]
              }
            ]
          },
          {
            "rule": "region",
            "description": "Ensures all page content is contained by landmarks",
            "impact": "moderate",
            "elements": [
              {
                "selector": ".clients-logos",
                "impact": "moderate",
                "must pass any of": [
                  {
                    "check": "region",
                    "description": "Some page content is not contained by landmarks",
                    "impact": "moderate"
                  }
                ]
              }
            ]
          },
          {
            "rule": "tabindex",
            "description": "Ensures tabindex attribute values are not greater than 0",
            "impact": "serious",
            "elements": [
              {
                "selector": "#skip_to_main_content",
                "impact": "serious",
                "must pass any of": [
                  {
                    "check": "tabindex",
                    "description": "Element has a tabindex greater than 0",
                    "impact": "serious"
                  }
                ]
              },
              {
                "selector": "#skip_to_main_menu",
                "impact": "serious",
                "must pass any of": [
                  {
                    "check": "tabindex",
                    "description": "Element has a tabindex greater than 0",
                    "impact": "serious"
                  }
                ]
              },
              {
                "selector": "#skip_to_bottom_menu",
                "impact": "serious",
                "must pass any of": [
                  {
                    "check": "tabindex",
                    "description": "Element has a tabindex greater than 0",
                    "impact": "serious"
                  }
                ]
              },
              {
                "selector": "#mk-aweb-open-panel",
                "impact": "serious",
                "must pass any of": [
                  {
                    "check": "tabindex",
                    "description": "Element has a tabindex greater than 0",
                    "impact": "serious"
                  }
                ]
              }
            ]
          }
        ]
      }
    },
    {
      "type": "launch",
      "which": "chromium",
      "what": "used for most tests"
    },
    {
      "type": "url",
      "which": "https://mk-sense.com/",
      "what": "Make-Sense",
      "result": "https://mk-sense.com/"
    },
    {
      "type": "test",
      "which": "bulk",
      "what": "count of visible elements",
      "url": "https://mk-sense.com/",
      "result": {
        "visibleElements": 352
      }
    },
    {
      "type": "test",
      "which": "embAc",
      "what": "active elements embedded in links or buttons",
      "withItems": true,
      "url": "https://mk-sense.com/",
      "result": {
        "totals": {
          "links": 0,
          "buttons": 0,
          "inputs": 0,
          "selects": 0
        },
        "items": []
      }
    },
    {
      "type": "test",
      "which": "focAll",
      "what": "focusable and Tab-focused elements",
      "url": "https://mk-sense.com/",
      "result": {
        "tabFocusables": 39,
        "tabFocused": 37,
        "discrepancy": -2
      }
    },
    {
      "type": "url",
      "which": "https://mk-sense.com/",
      "what": "Make-Sense",
      "result": "https://mk-sense.com/"
    },
    {
      "type": "test",
      "which": "focInd",
      "what": "focus indicators",
      "withItems": true,
      "revealAll": true,
      "url": "https://mk-sense.com/",
      "result": {
        "totals": {
          "total": 41,
          "types": {
            "indicatorMissing": {
              "total": 14,
              "tagNames": {
                "DIV": 4,
                "IFRAME": 2,
                "INPUT": 5,
                "BUTTON": 1,
                "A": 2
              }
            },
            "nonOutlinePresent": {
              "total": 3,
              "tagNames": {
                "A": 3
              }
            },
            "outlinePresent": {
              "total": 24,
              "tagNames": {
                "A": 24
              }
            }
          }
        },
        "items": {
          "indicatorMissing": [
            {
              "tagName": "DIV",
              "text": "PartnersOur Partners Love Us!Give your clients full digital accessibility - fast\nGive your clients f"
            },
            {
              "tagName": "DIV",
              "text": ""
            },
            {
              "tagName": "DIV",
              "text": ""
            },
            {
              "tagName": "DIV",
              "text": ""
            },
            {
              "tagName": "IFRAME",
              "text": ""
            },
            {
              "tagName": "INPUT",
              "text": ""
            },
            {
              "tagName": "INPUT",
              "text": ""
            },
            {
              "tagName": "INPUT",
              "text": ""
            },
            {
              "tagName": "INPUT",
              "text": ""
            },
            {
              "tagName": "INPUT",
              "text": ""
            },
            {
              "tagName": "BUTTON",
              "text": "Send My Accessibility Report"
            },
            {
              "tagName": "A",
              "text": "Stop"
            },
            {
              "tagName": "A",
              "text": "Play"
            },
            {
              "tagName": "IFRAME",
              "text": ""
            }
          ],
          "nonOutlinePresent": [
            {
              "tagName": "A",
              "text": "Your 7 Day Free Trial"
            },
            {
              "tagName": "A",
              "text": "Request Demo"
            },
            {
              "tagName": "A",
              "text": "Learn More"
            }
          ],
          "outlinePresent": [
            {
              "tagName": "A",
              "text": "Accept"
            },
            {
              "tagName": "A",
              "text": ""
            },
            {
              "tagName": "A",
              "text": "Home"
            },
            {
              "tagName": "A",
              "text": "Our Platform"
            },
            {
              "tagName": "A",
              "text": "About"
            },
            {
              "tagName": "A",
              "text": "WCAG Success Criteria"
            },
            {
              "tagName": "A",
              "text": "Packages"
            },
            {
              "tagName": "A",
              "text": "Partners"
            },
            {
              "tagName": "A",
              "text": "About Us"
            },
            {
              "tagName": "A",
              "text": "Blog"
            },
            {
              "tagName": "A",
              "text": "Contact"
            },
            {
              "tagName": "A",
              "text": "Login"
            },
            {
              "tagName": "A",
              "text": "WCAG 2.0 and WCAG2.1"
            },
            {
              "tagName": "A",
              "text": "Learn More"
            },
            {
              "tagName": "A",
              "text": "NEWCHIP ACCELERATOR PROGRAM SELECTS MAKE-SENSE FOR LATEST COHORT"
            },
            {
              "tagName": "A",
              "text": "Read More"
            },
            {
              "tagName": "A",
              "text": "DIGITAL ACCESSIBILITY PLATFORM MAKE-SENSE NOW AVAILABLE IN THE MICROSOFT AZURE MARKET PLACE"
            },
            {
              "tagName": "A",
              "text": "Read More"
            },
            {
              "tagName": "A",
              "text": "info@mk-sense.com​"
            },
            {
              "tagName": "A",
              "text": "Linkedin"
            },
            {
              "tagName": "A",
              "text": "Twitter"
            },
            {
              "tagName": "A",
              "text": "Instagram"
            },
            {
              "tagName": "A",
              "text": "Terms of Use"
            },
            {
              "tagName": "A",
              "text": "Privacy Policy"
            }
          ]
        }
      }
    },
    {
      "type": "url",
      "which": "https://mk-sense.com/",
      "what": "Make-Sense",
      "result": "https://mk-sense.com/"
    },
    {
      "type": "test",
      "which": "focOp",
      "what": "focusability and operability",
      "withItems": true,
      "url": "https://mk-sense.com/",
      "result": {
        "totals": {
          "total": 54,
          "types": {
            "onlyFocusable": {
              "total": 1,
              "tagNames": {
                "DIV": 1
              }
            },
            "onlyOperable": {
              "total": 7,
              "tagNames": {
                "A": 7
              }
            },
            "focusableAndOperable": {
              "total": 46,
              "tagNames": {
                "A": 31,
                "DIV": 3,
                "IFRAME": 2,
                "INPUT": 9,
                "BUTTON": 1
              }
            }
          }
        },
        "items": {
          "onlyFocusable": [
            {
              "tagName": "DIV",
              "id": "",
              "text": "PartnersOur Partners Love Us!Give your clients full digital accessibility - fast"
            }
          ],
          "onlyOperable": [
            {
              "tagName": "A",
              "id": "mk-aweb-open-panel",
              "text": ".a{fill:#04a0c4;}",
              "byTag": true,
              "byOnClick": false,
              "byPointer": true
            },
            {
              "tagName": "A",
              "id": "",
              "text": "Request Demo",
              "byTag": true,
              "byOnClick": false,
              "byPointer": true
            },
            {
              "tagName": "A",
              "id": "",
              "text": "Get Started",
              "byTag": true,
              "byOnClick": false,
              "byPointer": true
            },
            {
              "tagName": "A",
              "id": "",
              "text": "Request Demo",
              "byTag": true,
              "byOnClick": false,
              "byPointer": true
            },
            {
              "tagName": "A",
              "id": "",
              "text": "Get Started",
              "byTag": true,
              "byOnClick": false,
              "byPointer": true
            },
            {
              "tagName": "A",
              "id": "",
              "text": "Request Demo",
              "byTag": true,
              "byOnClick": false,
              "byPointer": true
            },
            {
              "tagName": "A",
              "id": "",
              "text": "Get Started",
              "byTag": true,
              "byOnClick": false,
              "byPointer": true
            }
          ],
          "focusableAndOperable": [
            {
              "tagName": "A",
              "id": "",
              "text": "<a class=\"mk-aweb-menu-close_accessibility_panel mk-aweb-menu-sprite style=\" '=\"",
              "byTag": true,
              "byOnClick": false,
              "byPointer": true
            },
            {
              "tagName": "A",
              "id": "hs-eu-confirmation-button",
              "text": "Accept",
              "byTag": true,
              "byOnClick": false,
              "byPointer": true
            },
            {
              "tagName": "A",
              "id": "",
              "text": "<a href=\"https://mk-sense.com\" style=\"cursor: default;\"><img src=\"https://mk-sen",
              "byTag": true,
              "byOnClick": false,
              "byPointer": true
            },
            {
              "tagName": "A",
              "id": "",
              "text": "Home",
              "byTag": true,
              "byOnClick": false,
              "byPointer": true
            },
            {
              "tagName": "A",
              "id": "",
              "text": "Our Platform",
              "byTag": true,
              "byOnClick": false,
              "byPointer": true
            },
            {
              "tagName": "A",
              "id": "",
              "text": "About",
              "byTag": true,
              "byOnClick": false,
              "byPointer": true
            },
            {
              "tagName": "A",
              "id": "",
              "text": "WCAG Success Criteria",
              "byTag": true,
              "byOnClick": false,
              "byPointer": true
            },
            {
              "tagName": "A",
              "id": "",
              "text": "Packages",
              "byTag": true,
              "byOnClick": false,
              "byPointer": true
            },
            {
              "tagName": "A",
              "id": "",
              "text": "Partners",
              "byTag": true,
              "byOnClick": false,
              "byPointer": true
            },
            {
              "tagName": "A",
              "id": "",
              "text": "About Us",
              "byTag": true,
              "byOnClick": false,
              "byPointer": true
            },
            {
              "tagName": "A",
              "id": "",
              "text": "Blog",
              "byTag": true,
              "byOnClick": false,
              "byPointer": true
            },
            {
              "tagName": "A",
              "id": "",
              "text": "Contact",
              "byTag": true,
              "byOnClick": false,
              "byPointer": true
            },
            {
              "tagName": "A",
              "id": "",
              "text": "Login",
              "byTag": true,
              "byOnClick": false,
              "byPointer": true
            },
            {
              "tagName": "A",
              "id": "",
              "text": "Request Your E-Tour!",
              "byTag": true,
              "byOnClick": false,
              "byPointer": true
            },
            {
              "tagName": "A",
              "id": "",
              "text": "Your 7 Day Free Trial",
              "byTag": true,
              "byOnClick": false,
              "byPointer": true
            },
            {
              "tagName": "A",
              "id": "",
              "text": "Request Demo",
              "byTag": true,
              "byOnClick": false,
              "byPointer": true
            },
            {
              "tagName": "A",
              "id": "",
              "text": "Learn More",
              "byTag": true,
              "byOnClick": false,
              "byPointer": true
            },
            {
              "tagName": "DIV",
              "id": "n2-ss-2-arrow-previous",
              "text": "<div style=\"--widget-offset:15px; cursor: default;\" class=\"n2-ss-widget n2-style",
              "byTag": false,
              "byOnClick": false,
              "byPointer": true
            },
            {
              "tagName": "DIV",
              "id": "n2-ss-2-arrow-next",
              "text": "<div style=\"--widget-offset:15px; cursor: default;\" class=\"n2-ss-widget n2-style",
              "byTag": false,
              "byOnClick": false,
              "byPointer": true
            },
            {
              "tagName": "DIV",
              "id": "",
              "text": "<div style=\"--widget-offset:15px; cursor: default;\" class=\"n2-ss-widget n2-style",
              "byTag": false,
              "byOnClick": false,
              "byPointer": true
            },
            {
              "tagName": "A",
              "id": "",
              "text": "WCAG 2.0 and WCAG2.1",
              "byTag": true,
              "byOnClick": false,
              "byPointer": true
            },
            {
              "tagName": "IFRAME",
              "id": "",
              "text": "<iframe loading=\"lazy\" src=\"https://www.youtube.com/embed/wZrFsLlqAMo?rel=0&amp;",
              "byTag": true,
              "byOnClick": false,
              "byPointer": false
            },
            {
              "tagName": "A",
              "id": "",
              "text": "Learn More",
              "byTag": true,
              "byOnClick": false,
              "byPointer": true
            },
            {
              "tagName": "A",
              "id": "listing-item-title-0",
              "text": "NEWCHIP ACCELERATOR PROGRAM SELECTS MAKE-SENSE FOR LATEST COHORT",
              "byTag": true,
              "byOnClick": false,
              "byPointer": true
            },
            {
              "tagName": "A",
              "id": "",
              "text": "Read More",
              "byTag": true,
              "byOnClick": false,
              "byPointer": true
            },
            {
              "tagName": "A",
              "id": "listing-item-title-1",
              "text": "DIGITAL ACCESSIBILITY PLATFORM MAKE-SENSE NOW AVAILABLE IN THE MICROSOFT AZURE M",
              "byTag": true,
              "byOnClick": false,
              "byPointer": true
            },
            {
              "tagName": "A",
              "id": "",
              "text": "Read More",
              "byTag": true,
              "byOnClick": false,
              "byPointer": true
            },
            {
              "tagName": "INPUT",
              "id": "wpforms-1678-field_1",
              "text": "<input type=\"text\" id=\"wpforms-1678-field_1\" class=\"wpforms-field-large wpforms-",
              "byTag": true,
              "byOnClick": false,
              "byPointer": false
            },
            {
              "tagName": "INPUT",
              "id": "wpforms-1678-field_2",
              "text": "<input type=\"text\" id=\"wpforms-1678-field_2\" class=\"wpforms-field-name-first wpf",
              "byTag": true,
              "byOnClick": false,
              "byPointer": false
            },
            {
              "tagName": "INPUT",
              "id": "wpforms-1678-field_2-last",
              "text": "<input type=\"text\" id=\"wpforms-1678-field_2-last\" class=\"wpforms-field-name-last",
              "byTag": true,
              "byOnClick": false,
              "byPointer": false
            },
            {
              "tagName": "INPUT",
              "id": "wpforms-1678-field_3",
              "text": "<input type=\"email\" id=\"wpforms-1678-field_3\" class=\"wpforms-field-large wpforms",
              "byTag": true,
              "byOnClick": false,
              "byPointer": false
            },
            {
              "tagName": "INPUT",
              "id": "wpforms-1678-field_5",
              "text": "<input type=\"tel\" pattern=\"\\d*\" id=\"wpforms-1678-field_5\" class=\"wpforms-field-l",
              "byTag": true,
              "byOnClick": false,
              "byPointer": false
            },
            {
              "tagName": "INPUT",
              "id": "wpforms-1678-field-hp",
              "text": "<input type=\"text\" name=\"wpforms[hp]\" id=\"wpforms-1678-field-hp\" class=\"wpforms-",
              "byTag": true,
              "byOnClick": false,
              "byPointer": false
            },
            {
              "tagName": "INPUT",
              "id": "",
              "text": "<input type=\"hidden\" name=\"wpforms[id]\" value=\"1678\">",
              "byTag": true,
              "byOnClick": false,
              "byPointer": false
            },
            {
              "tagName": "INPUT",
              "id": "",
              "text": "<input type=\"hidden\" name=\"wpforms[author]\" value=\"2\">",
              "byTag": true,
              "byOnClick": false,
              "byPointer": false
            },
            {
              "tagName": "INPUT",
              "id": "",
              "text": "<input type=\"hidden\" name=\"wpforms[post_id]\" value=\"1617\">",
              "byTag": true,
              "byOnClick": false,
              "byPointer": false
            },
            {
              "tagName": "BUTTON",
              "id": "wpforms-submit-1678",
              "text": "Send My Accessibility Report",
              "byTag": true,
              "byOnClick": false,
              "byPointer": false
            },
            {
              "tagName": "A",
              "id": "stop-btn",
              "text": "Stop",
              "byTag": true,
              "byOnClick": false,
              "byPointer": true
            },
            {
              "tagName": "A",
              "id": "play-btn",
              "text": "Play",
              "byTag": true,
              "byOnClick": false,
              "byPointer": true
            },
            {
              "tagName": "A",
              "id": "",
              "text": "info@mk-sense.com​",
              "byTag": true,
              "byOnClick": false,
              "byPointer": true
            },
            {
              "tagName": "A",
              "id": "",
              "text": "Linkedin",
              "byTag": true,
              "byOnClick": false,
              "byPointer": true
            },
            {
              "tagName": "A",
              "id": "",
              "text": "Twitter",
              "byTag": true,
              "byOnClick": false,
              "byPointer": true
            },
            {
              "tagName": "A",
              "id": "",
              "text": "Instagram",
              "byTag": true,
              "byOnClick": false,
              "byPointer": true
            },
            {
              "tagName": "A",
              "id": "",
              "text": "Terms of Use",
              "byTag": true,
              "byOnClick": false,
              "byPointer": true
            },
            {
              "tagName": "A",
              "id": "",
              "text": "Privacy Policy",
              "byTag": true,
              "byOnClick": false,
              "byPointer": true
            },
            {
              "tagName": "IFRAME",
              "id": "",
              "text": "<iframe owner=\"archetype\" title=\"archetype\" style=\"display: none; visibility: hi",
              "byTag": true,
              "byOnClick": false,
              "byPointer": false
            }
          ]
        }
      }
    },
    {
      "type": "url",
      "which": "https://mk-sense.com/",
      "what": "Make-Sense",
      "result": "https://mk-sense.com/"
    },
    {
      "type": "test",
      "which": "hover",
      "what": "hover-caused content additions",
      "withItems": true,
      "url": "https://mk-sense.com/",
      "result": {
        "totals": {
          "triggers": 2,
          "madeVisible": 0,
          "opacityChanged": 2,
          "opacityAffected": 10,
          "unhoverables": 14
        },
        "items": {
          "triggers": [
            {
              "tagName": "LI",
              "id": "menu-item-251",
              "text": "Our Platform About WCAG Success Criteria",
              "madeVisible": [],
              "opacityChanged": [
                {
                  "tagName": "UL",
                  "text": "About WCAG Success Criteria"
                }
              ]
            },
            {
              "tagName": "A",
              "id": "",
              "text": "Our Platform",
              "madeVisible": [],
              "opacityChanged": [
                {
                  "tagName": "UL",
                  "text": "About WCAG Success Criteria"
                }
              ]
            }
          ],
          "unhoverables": [
            {
              "tagName": "LI",
              "id": "",
              "text": "About"
            },
            {
              "tagName": "A",
              "id": "",
              "text": "About"
            },
            {
              "tagName": "LI",
              "id": "",
              "text": "WCAGSuccessCriteria"
            },
            {
              "tagName": "A",
              "id": "",
              "text": "WCAGSuccessCriteria"
            },
            {
              "tagName": "A",
              "id": "",
              "text": "RequestDemo"
            },
            {
              "tagName": "A",
              "id": "",
              "text": "LearnMore"
            },
            {
              "tagName": "A",
              "id": "",
              "text": "RequestDemo"
            },
            {
              "tagName": "A",
              "id": "",
              "text": "GetStarted"
            },
            {
              "tagName": "A",
              "id": "",
              "text": "RequestDemo"
            },
            {
              "tagName": "A",
              "id": "",
              "text": "GetStarted"
            },
            {
              "tagName": "LI",
              "id": "",
              "text": "TermsofUse"
            },
            {
              "tagName": "A",
              "id": "",
              "text": "TermsofUse"
            },
            {
              "tagName": "LI",
              "id": "",
              "text": "PrivacyPolicy"
            },
            {
              "tagName": "A",
              "id": "",
              "text": "PrivacyPolicy"
            }
          ]
        }
      }
    },
    {
      "type": "url",
      "which": "https://mk-sense.com/",
      "what": "Make-Sense",
      "result": "https://mk-sense.com/"
    },
    {
      "type": "test",
      "which": "labClash",
      "what": "labeling inconsistencies",
      "withItems": true,
      "url": "https://mk-sense.com/",
      "result": {
        "totals": {
          "mislabeled": 0,
          "unlabeled": 0,
          "wellLabeled": 7
        },
        "items": {
          "mislabeled": [],
          "unlabeled": [],
          "wellLabeled": [
            {
              "index": 0,
              "tagName": "INPUT",
              "type": "text",
              "labelType": "label",
              "texts": {
                "label": [
                  "Website (required)"
                ]
              }
            },
            {
              "index": 1,
              "tagName": "INPUT",
              "type": "text",
              "labelType": "label",
              "texts": {
                "label": [
                  "First (required)"
                ]
              }
            },
            {
              "index": 2,
              "tagName": "INPUT",
              "type": "text",
              "labelType": "label",
              "texts": {
                "label": [
                  "Last (required)"
                ]
              }
            },
            {
              "index": 3,
              "tagName": "INPUT",
              "type": "email",
              "labelType": "label",
              "texts": {
                "label": [
                  "Email Address (required)"
                ]
              }
            },
            {
              "index": 4,
              "tagName": "INPUT",
              "type": "tel",
              "labelType": "label",
              "texts": {
                "label": [
                  "Phone Number (required)"
                ]
              }
            },
            {
              "index": 5,
              "tagName": "INPUT",
              "type": "text",
              "labelType": "label",
              "texts": {
                "label": [
                  "Name"
                ]
              }
            },
            {
              "index": 6,
              "tagName": "BUTTON",
              "type": "submit",
              "texts": {
                "content": "Send My Accessibility Report"
              }
            }
          ]
        }
      }
    },
    {
      "type": "test",
      "which": "linkUl",
      "what": "inline-link underlining",
      "withItems": true,
      "url": "https://mk-sense.com/",
      "result": {
        "totals": {
          "links": 35,
          "inline": {
            "total": 13,
            "underlined": 0,
            "underlinedPercent": 0
          }
        },
        "items": {
          "underlined": [],
          "notUnderlined": [
            "Request Demo",
            "Learn More",
            "Request Demo",
            "Get Started",
            "Request Demo",
            "Get Started",
            "Request Demo",
            "Get Started",
            "WCAG 2.0 and WCAG2.1",
            "Stop",
            "Play",
            "Terms of Use",
            "Privacy Policy"
          ]
        }
      }
    },
    {
      "type": "test",
      "which": "menuNav",
      "what": "keyboard navigation between focusable menu items",
      "withItems": true,
      "url": "https://mk-sense.com/",
      "result": {
        "totals": {
          "navigations": {
            "all": {
              "total": 0,
              "correct": 0,
              "incorrect": 0
            },
            "specific": {
              "tab": {
                "total": 0,
                "correct": 0,
                "incorrect": 0
              },
              "left": {
                "total": 0,
                "correct": 0,
                "incorrect": 0
              },
              "right": {
                "total": 0,
                "correct": 0,
                "incorrect": 0
              },
              "up": {
                "total": 0,
                "correct": 0,
                "incorrect": 0
              },
              "down": {
                "total": 0,
                "correct": 0,
                "incorrect": 0
              },
              "home": {
                "total": 0,
                "correct": 0,
                "incorrect": 0
              },
              "end": {
                "total": 0,
                "correct": 0,
                "incorrect": 0
              }
            }
          },
          "menuItems": {
            "total": 0,
            "correct": 0,
            "incorrect": 0
          },
          "menus": {
            "total": 0,
            "correct": 0,
            "incorrect": 0
          }
        },
        "menuItems": {
          "incorrect": [],
          "correct": []
        }
      }
    },
    {
      "type": "url",
      "which": "https://mk-sense.com/",
      "what": "Make-Sense",
      "result": "https://mk-sense.com/"
    },
    {
      "type": "test",
      "which": "radioSet",
      "what": "fieldset grouping of radio buttons",
      "withItems": true,
      "url": "https://mk-sense.com/",
      "result": {
        "totals": {
          "total": 0,
          "inSet": 0,
          "percent": "N.A."
        },
        "items": {
          "inSet": [],
          "notInSet": []
        }
      }
    },
    {
      "type": "test",
      "which": "role",
      "what": "roles",
      "url": "https://mk-sense.com/",
      "result": {
        "roleElements": 19,
        "badRoleElements": 12,
        "tagNames": {
          "DIV": {
            "navigation": 2,
            "banner": 1,
            "region": 1,
            "button": 3
          },
          "A": {
            "button": 3
          },
          "NAV": {
            "navigation": 1
          },
          "MAIN": {
            "main": 1
          }
        }
      }
    },
    {
      "type": "test",
      "which": "styleDiff",
      "what": "style inconsistencies",
      "withItems": true,
      "url": "https://mk-sense.com/",
      "result": {
        "totals": {
          "h1": {
            "total": 2,
            "subtotals": [
              1,
              1
            ]
          },
          "h2": {
            "total": 7,
            "subtotals": [
              4,
              3
            ]
          },
          "h3": {
            "total": 1
          },
          "aInline": {
            "total": 13,
            "subtotals": [
              8,
              2,
              2,
              1
            ]
          },
          "aBlock": {
            "total": 22,
            "subtotals": [
              10,
              4,
              2,
              2,
              2,
              2
            ]
          },
          "button": {
            "total": 1
          }
        },
        "items": {
          "h1": {
            "fontWeight": {
              "400": 1,
              "700": 1
            },
            "lineHeight": {
              "0px": 1,
              "54px": 1
            },
            "fontSize": {
              "36px": 2,
              "0px": 1
            }
          },
          "h2": {
            "fontWeight": {
              "400": 3,
              "600": 4
            },
            "lineHeight": {
              "39px": 4,
              "54px": 3
            },
            "fontSize": {
              "30px": 30,
              "36px": 12
            }
          },
          "h3": {},
          "aInline": {
            "borderStyle": {
              "solid": 10,
              "none": 3
            },
            "borderWidth": {
              "0px": 11,
              "1px": 2
            },
            "lineHeight": {
              "30px": 8,
              "18.2px": 2,
              "20.8px": 2,
              "23.4px": 1
            },
            "fontSize": {
              "30px": 80,
              "14px": 20,
              "16px": 20,
              "18px": 10
            }
          },
          "aBlock": {
            "borderStyle": {
              "none": 18,
              "solid": 4
            },
            "borderWidth": {
              "0px": 18,
              "1px": 4
            },
            "fontWeight": {
              "400": 20,
              "700": 2
            },
            "lineHeight": {
              "23.4px": 12,
              "19.5px": 4,
              "20.8px": 2,
              "31.2px": 2,
              "24.96px": 2
            },
            "minHeight": {
              "0px": 20,
              "44px": 2
            },
            "fontSize": {
              "18px": 120,
              "15px": 40,
              "16px": 20,
              "24px": 20,
              "19.2px": 20
            }
          },
          "button": {}
        }
      }
    },
    {
      "type": "test",
      "which": "tabNav",
      "what": "keyboard navigation between tab elements",
      "withItems": true,
      "url": "https://mk-sense.com/",
      "result": {
        "totals": {
          "navigations": {
            "all": {
              "total": 0,
              "correct": 0,
              "incorrect": 0
            },
            "specific": {
              "tab": {
                "total": 0,
                "correct": 0,
                "incorrect": 0
              },
              "left": {
                "total": 0,
                "correct": 0,
                "incorrect": 0
              },
              "right": {
                "total": 0,
                "correct": 0,
                "incorrect": 0
              },
              "up": {
                "total": 0,
                "correct": 0,
                "incorrect": 0
              },
              "down": {
                "total": 0,
                "correct": 0,
                "incorrect": 0
              },
              "home": {
                "total": 0,
                "correct": 0,
                "incorrect": 0
              },
              "end": {
                "total": 0,
                "correct": 0,
                "incorrect": 0
              }
            }
          },
          "tabElements": {
            "total": 0,
            "correct": 0,
            "incorrect": 0
          },
          "tabLists": {
            "total": 0,
            "correct": 0,
            "incorrect": 0
          }
        },
        "tabElements": {
          "incorrect": [],
          "correct": []
        }
      }
    },
    {
      "type": "test",
      "which": "zIndex",
      "what": "z indexes",
      "withItems": true,
      "url": "https://mk-sense.com/",
      "result": {
        "totals": {
          "total": 86,
          "tagNames": {
            "A": 2,
            "DIV": 81,
            "NAV": 1,
            "UL": 1,
            "SS3-LOADER": 1
          }
        },
        "items": [
          {
            "tagName": "A",
            "id": "mk-aweb-open-panel",
            "text": ".a{fill:#04a0c4;}"
          },
          {
            "tagName": "DIV",
            "id": "mk-aweb-menu-accessibility-widget",
            "text": ""
          },
          {
            "tagName": "A",
            "id": "",
            "text": ""
          },
          {
            "tagName": "DIV",
            "id": "hs-eu-cookie-confirmation",
            "text": "This website stores cookies on your computer. These cookies are used to collect information about ho"
          },
          {
            "tagName": "NAV",
            "id": "",
            "text": "Home\nOur Platform About WCAG Success Criteria Packages\nPartners\nAbout Us\nBlog\nContact Login"
          },
          {
            "tagName": "UL",
            "id": "",
            "text": "About WCAG Success Criteria"
          },
          {
            "tagName": "DIV",
            "id": "n2-ss-2-align",
            "text": "PartnersOur Partners Love Us!Give your clients full digital accessibility - fast\nGive your clients f"
          },
          {
            "tagName": "DIV",
            "id": "n2-ss-2",
            "text": "PartnersOur Partners Love Us!Give your clients full digital accessibility - fast\nGive your clients f"
          },
          {
            "tagName": "DIV",
            "id": "",
            "text": "PartnersOur Partners Love Us!Give your clients full digital accessibility - fast\nGive your clients f"
          },
          {
            "tagName": "DIV",
            "id": "",
            "text": "PartnersOur Partners Love Us!Give your clients full digital accessibility - fast\nGive your clients f"
          },
          {
            "tagName": "DIV",
            "id": "",
            "text": ""
          },
          {
            "tagName": "DIV",
            "id": "",
            "text": ""
          },
          {
            "tagName": "DIV",
            "id": "",
            "text": ""
          },
          {
            "tagName": "DIV",
            "id": "",
            "text": ""
          },
          {
            "tagName": "DIV",
            "id": "",
            "text": ""
          },
          {
            "tagName": "DIV",
            "id": "",
            "text": ""
          },
          {
            "tagName": "DIV",
            "id": "",
            "text": ""
          },
          {
            "tagName": "DIV",
            "id": "",
            "text": ""
          },
          {
            "tagName": "DIV",
            "id": "",
            "text": ""
          },
          {
            "tagName": "DIV",
            "id": "",
            "text": ""
          },
          {
            "tagName": "DIV",
            "id": "",
            "text": ""
          },
          {
            "tagName": "DIV",
            "id": "",
            "text": ""
          },
          {
            "tagName": "DIV",
            "id": "",
            "text": ""
          },
          {
            "tagName": "DIV",
            "id": "",
            "text": "PartnersOur Partners Love Us!Give your clients full digital accessibility - fast\nGive your clients f"
          },
          {
            "tagName": "DIV",
            "id": "",
            "text": "PartnersOur Partners Love Us!Give your clients full digital accessibility - fast\nGive your clients f"
          },
          {
            "tagName": "DIV",
            "id": "",
            "text": "Partners"
          },
          {
            "tagName": "DIV",
            "id": "",
            "text": "Our Partners Love Us!Give your clients full digital accessibility - fast\nGive your clients full digi"
          },
          {
            "tagName": "DIV",
            "id": "",
            "text": "Our Partners Love Us!Give your clients full digital accessibility - fast\nGive your clients full digi"
          },
          {
            "tagName": "DIV",
            "id": "",
            "text": "Our Partners Love Us!Give your clients full digital accessibility - fast\nGive your clients full digi"
          },
          {
            "tagName": "DIV",
            "id": "",
            "text": "Our Partners Love Us!Give your clients full digital accessibility - fast\nGive your clients full digi"
          },
          {
            "tagName": "DIV",
            "id": "",
            "text": "Our Partners Love Us!Give your clients full digital accessibility - fast\nGive your clients full digi"
          },
          {
            "tagName": "DIV",
            "id": "",
            "text": "Our Partners Love Us!"
          },
          {
            "tagName": "DIV",
            "id": "",
            "text": "Give your clients full digital accessibility - fast\nGive your clients full digital accessibility - f"
          },
          {
            "tagName": "DIV",
            "id": "",
            "text": "Request DemoLearn More"
          },
          {
            "tagName": "DIV",
            "id": "",
            "text": "Request DemoLearn More"
          },
          {
            "tagName": "DIV",
            "id": "",
            "text": "Request Demo"
          },
          {
            "tagName": "DIV",
            "id": "",
            "text": "Learn More"
          },
          {
            "tagName": "DIV",
            "id": "",
            "text": "Slide 1Make-Sense: Automated Digital Accessibility PlatformMeet accessibility regulations | Ensure c"
          },
          {
            "tagName": "DIV",
            "id": "",
            "text": "Slide 1"
          },
          {
            "tagName": "DIV",
            "id": "",
            "text": "Make-Sense: Automated Digital Accessibility PlatformMeet accessibility regulations | Ensure continuo"
          },
          {
            "tagName": "DIV",
            "id": "",
            "text": "Make-Sense: Automated Digital Accessibility PlatformMeet accessibility regulations | Ensure continuo"
          },
          {
            "tagName": "DIV",
            "id": "",
            "text": "Make-Sense: Automated Digital Accessibility PlatformMeet accessibility regulations | Ensure continuo"
          },
          {
            "tagName": "DIV",
            "id": "",
            "text": "Make-Sense: Automated Digital Accessibility PlatformMeet accessibility regulations | Ensure continuo"
          },
          {
            "tagName": "DIV",
            "id": "",
            "text": "Make-Sense: Automated Digital Accessibility PlatformMeet accessibility regulations | Ensure continuo"
          },
          {
            "tagName": "DIV",
            "id": "",
            "text": "Make-Sense: Automated Digital Accessibility Platform"
          },
          {
            "tagName": "DIV",
            "id": "",
            "text": "Meet accessibility regulations | Ensure continuous accessibility | Make a Social Impact\nMeet accessi"
          },
          {
            "tagName": "DIV",
            "id": "",
            "text": "Request DemoGet Started"
          },
          {
            "tagName": "DIV",
            "id": "",
            "text": "Request DemoGet Started"
          },
          {
            "tagName": "DIV",
            "id": "",
            "text": "Request Demo"
          },
          {
            "tagName": "DIV",
            "id": "",
            "text": "Get Started"
          },
          {
            "tagName": "DIV",
            "id": "",
            "text": "Slide 2The Easy Path to AccessibilityAutomated fixes | User-friendly dashboard | Deploy with just 1 "
          },
          {
            "tagName": "DIV",
            "id": "",
            "text": "Slide 2"
          },
          {
            "tagName": "DIV",
            "id": "",
            "text": "The Easy Path to AccessibilityAutomated fixes | User-friendly dashboard | Deploy with just 1 line of"
          },
          {
            "tagName": "DIV",
            "id": "",
            "text": "The Easy Path to AccessibilityAutomated fixes | User-friendly dashboard | Deploy with just 1 line of"
          },
          {
            "tagName": "DIV",
            "id": "",
            "text": "The Easy Path to AccessibilityAutomated fixes | User-friendly dashboard | Deploy with just 1 line of"
          },
          {
            "tagName": "DIV",
            "id": "",
            "text": "The Easy Path to AccessibilityAutomated fixes | User-friendly dashboard | Deploy with just 1 line of"
          },
          {
            "tagName": "DIV",
            "id": "",
            "text": "The Easy Path to AccessibilityAutomated fixes | User-friendly dashboard | Deploy with just 1 line of"
          },
          {
            "tagName": "DIV",
            "id": "",
            "text": "The Easy Path to Accessibility"
          },
          {
            "tagName": "DIV",
            "id": "",
            "text": "Automated fixes | User-friendly dashboard | Deploy with just 1 line of code\nAutomated fixes | User-f"
          },
          {
            "tagName": "DIV",
            "id": "",
            "text": "Request DemoGet Started"
          },
          {
            "tagName": "DIV",
            "id": "",
            "text": "Request DemoGet Started"
          },
          {
            "tagName": "DIV",
            "id": "",
            "text": "Request Demo"
          },
          {
            "tagName": "DIV",
            "id": "",
            "text": "Get Started"
          },
          {
            "tagName": "DIV",
            "id": "",
            "text": "Slide 3The Most Secure Platform AvailableISO 27001 Security Information certified ISO 27001 Security"
          },
          {
            "tagName": "DIV",
            "id": "",
            "text": "Slide 3"
          },
          {
            "tagName": "DIV",
            "id": "",
            "text": "The Most Secure Platform AvailableISO 27001 Security Information certified ISO 27001 Security Inform"
          },
          {
            "tagName": "DIV",
            "id": "",
            "text": "The Most Secure Platform AvailableISO 27001 Security Information certified ISO 27001 Security Inform"
          },
          {
            "tagName": "DIV",
            "id": "",
            "text": "The Most Secure Platform AvailableISO 27001 Security Information certified ISO 27001 Security Inform"
          },
          {
            "tagName": "DIV",
            "id": "",
            "text": "The Most Secure Platform AvailableISO 27001 Security Information certified ISO 27001 Security Inform"
          },
          {
            "tagName": "DIV",
            "id": "",
            "text": "The Most Secure Platform AvailableISO 27001 Security Information certified ISO 27001 Security Inform"
          },
          {
            "tagName": "DIV",
            "id": "",
            "text": "The Most Secure Platform Available"
          },
          {
            "tagName": "DIV",
            "id": "",
            "text": "ISO 27001 Security Information certified ISO 27001 Security Information certified ISO 27001 Security"
          },
          {
            "tagName": "DIV",
            "id": "",
            "text": "Request DemoGet Started"
          },
          {
            "tagName": "DIV",
            "id": "",
            "text": "Request DemoGet Started"
          },
          {
            "tagName": "DIV",
            "id": "",
            "text": "Request Demo"
          },
          {
            "tagName": "DIV",
            "id": "",
            "text": "Get Started"
          },
          {
            "tagName": "DIV",
            "id": "",
            "text": "Partners"
          },
          {
            "tagName": "DIV",
            "id": "",
            "text": "Partners"
          },
          {
            "tagName": "DIV",
            "id": "",
            "text": ""
          },
          {
            "tagName": "DIV",
            "id": "n2-ss-2-arrow-previous",
            "text": ""
          },
          {
            "tagName": "DIV",
            "id": "",
            "text": ""
          },
          {
            "tagName": "DIV",
            "id": "n2-ss-2-arrow-next",
            "text": ""
          },
          {
            "tagName": "DIV",
            "id": "",
            "text": ""
          },
          {
            "tagName": "DIV",
            "id": "",
            "text": ""
          },
          {
            "tagName": "SS3-LOADER",
            "id": "",
            "text": ""
          },
          {
            "tagName": "DIV",
            "id": "",
            "text": "StopPlay"
          }
        ]
      }
    },
    {
      "type": "test",
      "which": "ibm",
      "withItems": true,
      "what": "IBM Accessibility Checker",
      "url": "https://mk-sense.com/",
      "result": {
        "content": {
          "totals": {
            "violation": 10,
            "recommendation": 0,
            "ignored": 0
          },
          "items": [
            {
              "ruleId": "WCAG20_Input_LabelBefore",
              "path": {
                "dom": "/html[1]/body[1]/main[1]/div[1]/div[1]/article[1]/div[1]/section[6]/div[1]/div[2]/div[1]/form[1]/div[1]/div[2]/div[1]/div[2]/input[1]",
                "aria": "/document[1]/main[1]/article[1]/region[6]/form[1]/textbox[3]"
              },
              "message": "Label text is located after its associated text input or <select> element",
              "bounds": {
                "left": 331,
                "top": 3733,
                "height": 38,
                "width": 213
              },
              "snippet": "<input required=\"\" placeholder=\"Last\" name=\"wpforms[fields][2][last]\" class=\"wpforms-field-name-last wpforms-field-required\" id=\"wpforms-1678-field_2-last\" type=\"text\">",
              "level": "violation"
            },
            {
              "ruleId": "WCAG20_Input_LabelBefore",
              "path": {
                "dom": "/html[1]/body[1]/main[1]/div[1]/div[1]/article[1]/div[1]/section[6]/div[1]/div[2]/div[1]/form[1]/div[1]/div[2]/div[1]/div[1]/input[1]",
                "aria": "/document[1]/main[1]/article[1]/region[6]/form[1]/textbox[2]"
              },
              "message": "Label text is located after its associated text input or <select> element",
              "bounds": {
                "left": 100,
                "top": 3733,
                "height": 38,
                "width": 213
              },
              "snippet": "<input required=\"\" placeholder=\"First\" name=\"wpforms[fields][2][first]\" class=\"wpforms-field-name-first wpforms-field-required\" id=\"wpforms-1678-field_2\" type=\"text\">",
              "level": "violation"
            },
            {
              "ruleId": "Rpt_Aria_OrphanedContent_Native_Host_Sematics",
              "path": {
                "dom": "/html[1]/body[1]/div[4]/div[1]/ul[1]",
                "aria": "/document[1]/list[4]"
              },
              "message": "Content is not within a landmark element",
              "bounds": {
                "left": 0,
                "top": 4218,
                "height": 50,
                "width": 800
              },
              "snippet": "<ul class=\"logos-carousel\">",
              "level": "violation"
            },
            {
              "ruleId": "Rpt_Aria_OrphanedContent_Native_Host_Sematics",
              "path": {
                "dom": "/html[1]/body[1]/div[4]/div[1]/div[1]/a[1]",
                "aria": "/document[1]"
              },
              "message": "Content is not within a landmark element",
              "bounds": {
                "left": 0,
                "top": 4290,
                "height": 29,
                "width": 42
              },
              "snippet": "<a id=\"stop-btn\">",
              "level": "violation"
            },
            {
              "ruleId": "Rpt_Aria_OneBannerInSiblingSet_Implicit",
              "path": {
                "dom": "/html[1]/body[1]/header[1]",
                "aria": "/document[1]/banner[2]"
              },
              "message": "There is more than one element with \"banner\" role on the page",
              "bounds": {
                "left": 0,
                "top": 0,
                "height": 214,
                "width": 800
              },
              "snippet": "<header>",
              "level": "violation"
            },
            {
              "ruleId": "Rpt_Aria_OneBannerInSiblingSet_Implicit",
              "path": {
                "dom": "/html[1]/body[1]/div[2]",
                "aria": "/document[1]/banner[1]"
              },
              "message": "There is more than one element with \"banner\" role on the page",
              "bounds": {
                "left": 0,
                "top": 441,
                "height": 159,
                "width": 800
              },
              "snippet": "<div data-nosnippet=\"\" class=\"hs-cookie-notification-position-bottom\" id=\"hs-eu-cookie-confirmation\" role=\"banner\">",
              "level": "violation"
            },
            {
              "ruleId": "Rpt_Aria_MultipleNavigationLandmarks_Implicit",
              "path": {
                "dom": "/html[1]/body[1]/header[1]/div[1]/div[1]/nav[1]",
                "aria": "/document[1]/banner[2]/navigation[1]"
              },
              "message": "Multiple elements with \"navigation\" role do not have unique labels",
              "bounds": {
                "left": 52,
                "top": 130,
                "height": 54,
                "width": 709
              },
              "snippet": "<nav role=\"navigation\" data-mk-aweb=\"main-menu\">",
              "level": "violation"
            },
            {
              "ruleId": "Rpt_Aria_MultipleBannerLandmarks_Implicit",
              "path": {
                "dom": "/html[1]/body[1]/header[1]",
                "aria": "/document[1]/banner[2]"
              },
              "message": "Multiple elements with \"banner\" role do not have unique labels",
              "bounds": {
                "left": 0,
                "top": 0,
                "height": 214,
                "width": 800
              },
              "snippet": "<header>",
              "level": "violation"
            },
            {
              "ruleId": "Rpt_Aria_MultipleBannerLandmarks_Implicit",
              "path": {
                "dom": "/html[1]/body[1]/div[2]",
                "aria": "/document[1]/banner[1]"
              },
              "message": "Multiple elements with \"banner\" role do not have unique labels",
              "bounds": {
                "left": 0,
                "top": 441,
                "height": 159,
                "width": 800
              },
              "snippet": "<div data-nosnippet=\"\" class=\"hs-cookie-notification-position-bottom\" id=\"hs-eu-cookie-confirmation\" role=\"banner\">",
              "level": "violation"
            },
            {
              "ruleId": "IBMA_Color_Contrast_WCAG2AA",
              "path": {
                "dom": "/html[1]/body[1]/div[2]/div[1]/div[2]/div[1]/a[1]",
                "aria": "/document[1]/banner[1]/button[1]"
              },
              "message": "Text contrast of 3.09 with its background is less than the WCAG AA minimum requirements for text of size 12px and weight of 400",
              "bounds": {
                "left": 364,
                "top": 534,
                "height": 40,
                "width": 73
              },
              "snippet": "<a role=\"button\" id=\"hs-eu-confirmation-button\" href=\"javascript:void(0);\">",
              "level": "violation"
            }
          ]
        },
        "url": {
          "totals": {
            "violation": 18,
            "recommendation": 0,
            "ignored": 0
          },
          "items": [
            {
              "ruleId": "WCAG20_Input_LabelBefore",
              "path": {
                "dom": "/html[1]/body[1]/main[1]/div[1]/div[1]/article[1]/div[1]/section[6]/div[1]/div[2]/div[1]/form[1]/div[1]/div[2]/div[1]/div[2]/input[1]",
                "aria": "/document[1]/main[1]/article[1]/region[6]/form[1]/textbox[3]"
              },
              "message": "Label text is located after its associated text input or <select> element",
              "bounds": {
                "left": 331,
                "top": 3685,
                "height": 38,
                "width": 213
              },
              "snippet": "<input required=\"\" placeholder=\"Last\" name=\"wpforms[fields][2][last]\" class=\"wpforms-field-name-last wpforms-field-required\" id=\"wpforms-1678-field_2-last\" type=\"text\">",
              "level": "violation"
            },
            {
              "ruleId": "WCAG20_Input_LabelBefore",
              "path": {
                "dom": "/html[1]/body[1]/main[1]/div[1]/div[1]/article[1]/div[1]/section[6]/div[1]/div[2]/div[1]/form[1]/div[1]/div[2]/div[1]/div[1]/input[1]",
                "aria": "/document[1]/main[1]/article[1]/region[6]/form[1]/textbox[2]"
              },
              "message": "Label text is located after its associated text input or <select> element",
              "bounds": {
                "left": 100,
                "top": 3685,
                "height": 38,
                "width": 213
              },
              "snippet": "<input required=\"\" placeholder=\"First\" name=\"wpforms[fields][2][first]\" class=\"wpforms-field-name-first wpforms-field-required\" id=\"wpforms-1678-field_2\" type=\"text\">",
              "level": "violation"
            },
            {
              "ruleId": "WCAG20_Img_HasAlt",
              "path": {
                "dom": "/html[1]/body[1]/footer[1]/div[1]/div[1]/div[5]/img[1]",
                "aria": "/document[1]/contentinfo[1]/img[2]"
              },
              "message": "Image does not have an 'alt' attribute short text alternative",
              "bounds": {
                "left": 10,
                "top": 4713,
                "height": 47,
                "width": 143
              },
              "snippet": "<img class=\"img-responsive\" src=\"/wp-content/themes/mobilitpro/images/footer-logo-iso.png\">",
              "level": "violation"
            },
            {
              "ruleId": "WCAG20_Img_HasAlt",
              "path": {
                "dom": "/html[1]/body[1]/footer[1]/div[1]/div[1]/div[1]/img[1]",
                "aria": "/document[1]/contentinfo[1]/img[1]"
              },
              "message": "Image does not have an 'alt' attribute short text alternative",
              "bounds": {
                "left": 10,
                "top": 4251,
                "height": 46,
                "width": 185
              },
              "snippet": "<img class=\"img-responsive\" src=\"/wp-content/themes/mobilitpro/images/footer-logo-make-sense.png\">",
              "level": "violation"
            },
            {
              "ruleId": "WCAG20_Frame_HasTitle",
              "path": {
                "dom": "/html[1]/body[1]/main[1]/div[1]/div[1]/article[1]/div[1]/section[2]/div[1]/div[1]/div[2]/div[1]/iframe[1]",
                "aria": "/document[1]/main[1]/article[1]/region[2]"
              },
              "message": "Inline frame does not have a 'title' attribute",
              "bounds": {
                "left": 408,
                "top": 602,
                "height": 229,
                "width": 353
              },
              "snippet": "<iframe allowfullscreen=\"allowfullscreen\" frameborder=\"0\" height=\"315\" width=\"560\" src=\"https://www.youtube.com/embed/wZrFsLlqAMo?rel=0&modestbranding=1\" loading=\"lazy\">",
              "level": "violation"
            },
            {
              "ruleId": "WCAG20_A_HasText",
              "path": {
                "dom": "/html[1]/body[1]/main[1]/div[1]/div[1]/article[1]/div[1]/section[5]/div[1]/div[1]/div[1]/div[2]/a[1]",
                "aria": "/document[1]/main[1]/article[1]/region[5]/link[4]"
              },
              "message": "Hyperlink has no link text, label or image with a text alternative",
              "bounds": {
                "left": 40,
                "top": 2982,
                "height": 140,
                "width": 280
              },
              "snippet": "<a href=\"https://mk-sense.com/digital-accessibility-platform-make-sense-now-available-in-the-microsoft-azure-market-place/\" class=\"image\">",
              "level": "violation"
            },
            {
              "ruleId": "WCAG20_A_HasText",
              "path": {
                "dom": "/html[1]/body[1]/main[1]/div[1]/div[1]/article[1]/div[1]/section[5]/div[1]/div[1]/div[1]/div[1]/a[1]",
                "aria": "/document[1]/main[1]/article[1]/region[5]/link[1]"
              },
              "message": "Hyperlink has no link text, label or image with a text alternative",
              "bounds": {
                "left": 40,
                "top": 2678,
                "height": 140,
                "width": 280
              },
              "snippet": "<a href=\"https://mk-sense.com/newchip-accelerator-program-selects-make-sense-for-latest-cohort/\" class=\"image\">",
              "level": "violation"
            },
            {
              "ruleId": "RPT_Label_UniqueFor",
              "path": {
                "dom": "/html[1]/body[1]/main[1]/div[1]/div[1]/article[1]/div[1]/section[6]/div[1]/div[2]/div[1]/form[1]/div[1]/div[2]/div[1]/div[1]/label[1]",
                "aria": "/document[1]/main[1]/article[1]/region[6]/form[1]"
              },
              "message": "Form control has more than one label",
              "bounds": {
                "left": -99899,
                "top": -96310,
                "height": 16,
                "width": 27
              },
              "snippet": "<label class=\"wpforms-field-sublabel after wpforms-sublabel-hide\" for=\"wpforms-1678-field_2\">",
              "level": "violation"
            },
            {
              "ruleId": "Rpt_Aria_OrphanedContent_Native_Host_Sematics",
              "path": {
                "dom": "/html[1]/body[1]/div[4]/div[1]/div[1]/a[1]",
                "aria": "/document[1]"
              },
              "message": "Content is not within a landmark element",
              "bounds": {
                "left": 0,
                "top": 4174,
                "height": 29,
                "width": 42
              },
              "snippet": "<a id=\"stop-btn\">",
              "level": "violation"
            },
            {
              "ruleId": "Rpt_Aria_OneBannerInSiblingSet_Implicit",
              "path": {
                "dom": "/html[1]/body[1]/header[1]",
                "aria": "/document[1]/banner[2]"
              },
              "message": "There is more than one element with \"banner\" role on the page",
              "bounds": {
                "left": 0,
                "top": 0,
                "height": 214,
                "width": 800
              },
              "snippet": "<header>",
              "level": "violation"
            },
            {
              "ruleId": "Rpt_Aria_OneBannerInSiblingSet_Implicit",
              "path": {
                "dom": "/html[1]/body[1]/div[1]",
                "aria": "/document[1]/banner[1]"
              },
              "message": "There is more than one element with \"banner\" role on the page",
              "bounds": {
                "left": 0,
                "top": 441,
                "height": 159,
                "width": 800
              },
              "snippet": "<div data-nosnippet=\"\" class=\"hs-cookie-notification-position-bottom\" id=\"hs-eu-cookie-confirmation\" role=\"banner\">",
              "level": "violation"
            },
            {
              "ruleId": "Rpt_Aria_MultipleBannerLandmarks_Implicit",
              "path": {
                "dom": "/html[1]/body[1]/header[1]",
                "aria": "/document[1]/banner[2]"
              },
              "message": "Multiple elements with \"banner\" role do not have unique labels",
              "bounds": {
                "left": 0,
                "top": 0,
                "height": 214,
                "width": 800
              },
              "snippet": "<header>",
              "level": "violation"
            },
            {
              "ruleId": "Rpt_Aria_MultipleBannerLandmarks_Implicit",
              "path": {
                "dom": "/html[1]/body[1]/div[1]",
                "aria": "/document[1]/banner[1]"
              },
              "message": "Multiple elements with \"banner\" role do not have unique labels",
              "bounds": {
                "left": 0,
                "top": 441,
                "height": 159,
                "width": 800
              },
              "snippet": "<div data-nosnippet=\"\" class=\"hs-cookie-notification-position-bottom\" id=\"hs-eu-cookie-confirmation\" role=\"banner\">",
              "level": "violation"
            },
            {
              "ruleId": "IBMA_Color_Contrast_WCAG2AA",
              "path": {
                "dom": "/html[1]/body[1]/main[1]/div[1]/div[1]/article[1]/div[1]/section[6]/div[1]/div[2]/div[1]/form[1]/div[1]/div[4]/label[1]/span[1]",
                "aria": "/document[1]/main[1]/article[1]/region[6]/form[1]"
              },
              "message": "Text contrast of 1.16 with its background is less than the WCAG AA minimum requirements for text of size 16px and weight of 400",
              "bounds": {
                "left": -99869,
                "top": -99761,
                "height": 22,
                "width": 9
              },
              "snippet": "<span class=\"wpforms-required-label\">",
              "level": "violation"
            },
            {
              "ruleId": "IBMA_Color_Contrast_WCAG2AA",
              "path": {
                "dom": "/html[1]/body[1]/main[1]/div[1]/div[1]/article[1]/div[1]/section[6]/div[1]/div[2]/div[1]/form[1]/div[1]/div[3]/label[1]/span[1]",
                "aria": "/document[1]/main[1]/article[1]/region[6]/form[1]"
              },
              "message": "Text contrast of 1.16 with its background is less than the WCAG AA minimum requirements for text of size 16px and weight of 400",
              "bounds": {
                "left": -99878,
                "top": -99761,
                "height": 22,
                "width": 9
              },
              "snippet": "<span class=\"wpforms-required-label\">",
              "level": "violation"
            },
            {
              "ruleId": "IBMA_Color_Contrast_WCAG2AA",
              "path": {
                "dom": "/html[1]/body[1]/main[1]/div[1]/div[1]/article[1]/div[1]/section[6]/div[1]/div[2]/div[1]/form[1]/div[1]/div[2]/label[1]/span[1]",
                "aria": "/document[1]/main[1]/article[1]/region[6]/form[1]"
              },
              "message": "Text contrast of 1.16 with its background is less than the WCAG AA minimum requirements for text of size 16px and weight of 400",
              "bounds": {
                "left": -99942,
                "top": -99761,
                "height": 22,
                "width": 9
              },
              "snippet": "<span class=\"wpforms-required-label\">",
              "level": "violation"
            },
            {
              "ruleId": "IBMA_Color_Contrast_WCAG2AA",
              "path": {
                "dom": "/html[1]/body[1]/main[1]/div[1]/div[1]/article[1]/div[1]/section[6]/div[1]/div[2]/div[1]/form[1]/div[1]/div[1]/label[1]/span[1]",
                "aria": "/document[1]/main[1]/article[1]/region[6]/form[1]"
              },
              "message": "Text contrast of 1.16 with its background is less than the WCAG AA minimum requirements for text of size 16px and weight of 400",
              "bounds": {
                "left": -99891,
                "top": -99761,
                "height": 22,
                "width": 9
              },
              "snippet": "<span class=\"wpforms-required-label\">",
              "level": "violation"
            },
            {
              "ruleId": "IBMA_Color_Contrast_WCAG2AA",
              "path": {
                "dom": "/html[1]/body[1]/div[1]/div[1]/div[2]/div[1]/a[1]",
                "aria": "/document[1]/banner[1]/button[1]"
              },
              "message": "Text contrast of 3.09 with its background is less than the WCAG AA minimum requirements for text of size 12px and weight of 400",
              "bounds": {
                "left": 364,
                "top": 534,
                "height": 40,
                "width": 73
              },
              "snippet": "<a role=\"button\" id=\"hs-eu-confirmation-button\" href=\"javascript:void(0);\">",
              "level": "violation"
            }
          ]
        }
      }
    },
    {
      "type": "url",
      "which": "https://mk-sense.com/",
      "what": "Make-Sense",
      "result": "https://mk-sense.com/"
    },
    {
      "type": "test",
      "which": "wave",
      "reportType": 4,
      "what": "WAVE",
      "url": "https://mk-sense.com/",
      "result": {
        "status": {
          "success": true,
          "httpstatuscode": 200
        },
        "statistics": {
          "pagetitle": "Digital Accessibility Platform - Make-Sense Web Accessibility Solutions:WCAG 2.0, Section 508 & ADA Compliance",
          "pageurl": "https://mk-sense.com/",
          "time": 4.34,
          "creditsremaining": 986,
          "allitemcount": 121,
          "totalelements": 584,
          "waveurl": "http://wave.webaim.org/report?url=https://mk-sense.com/",
          "domid": "1af7d0c022c049a9dc6c12721411fcfb"
        },
        "categories": {
          "error": {
            "description": "Errors",
            "count": 0,
            "items": []
          },
          "contrast": {
            "description": "Contrast Errors",
            "count": 1,
            "items": {
              "contrast": {
                "id": "contrast",
                "description": "Very low contrast",
                "count": 1,
                "selectors": [
                  "HTML > HEAD:first-child + BODY > DIV#hs-eu-cookie-confirmation > DIV#hs-eu-cookie-confirmation-inner > DIV#hs-en-cookie-confirmation-buttons-area > DIV#hs-eu-cookie-confirmation-button-group > A#hs-eu-confirmation-button"
                ],
                "contrastdata": [
                  [
                    3.08,
                    "#ffffff",
                    "#4a99d4",
                    false
                  ]
                ]
              }
            }
          },
          "alert": {
            "description": "Alerts",
            "count": 20,
            "items": {
              "alt_duplicate": {
                "id": "alt_duplicate",
                "description": "A nearby image has the same alternative text",
                "count": 3,
                "selectors": [
                  "HTML > HEAD:first-child + BODY > MAIN#main > DIV:first-child > DIV#primary > ARTICLE#post-1617 > HEADER:first-child + DIV > SECTION#firstSection > H1:first-child + DIV > DIV:first-child > SS3-FORCE-FULL-WIDTH:first-child > DIV:first-child > DIV#n2-ss-2-align > DIV:first-child > DIV#n2-ss-2 > DIV:first-child > DIV:first-child > DIV:first-child > DIV:first-child > DIV:first-child > DIV:first-child + DIV > DIV:first-child > PICTURE:first-child > IMG:first-child",
                  "HTML > HEAD:first-child + BODY > MAIN#main > DIV:first-child > DIV#primary > ARTICLE#post-1617 > HEADER:first-child + DIV > SECTION#firstSection > H1:first-child + DIV > DIV:first-child > SS3-FORCE-FULL-WIDTH:first-child > DIV:first-child > DIV#n2-ss-2-align > DIV:first-child > DIV#n2-ss-2 > DIV:first-child > DIV:first-child > DIV:first-child > DIV:first-child > DIV:first-child > DIV:first-child + DIV + DIV > DIV:first-child > PICTURE:first-child > IMG:first-child",
                  "HTML > HEAD:first-child + BODY > MAIN#main > DIV:first-child > DIV#primary > ARTICLE#post-1617 > HEADER:first-child + DIV > SECTION#firstSection > H1:first-child + DIV > DIV:first-child > SS3-FORCE-FULL-WIDTH:first-child > DIV:first-child > DIV#n2-ss-2-align > DIV:first-child > DIV#n2-ss-2 > DIV:first-child > DIV:first-child > DIV:first-child > DIV:first-child > DIV:first-child > DIV:first-child + DIV + DIV + DIV > DIV:first-child > PICTURE:first-child > IMG:first-child"
                ]
              },
              "heading_possible": {
                "id": "heading_possible",
                "description": "Possible heading",
                "count": 3,
                "selectors": [
                  "HTML > HEAD:first-child + BODY > MAIN#main > DIV:first-child > DIV#primary > ARTICLE#post-1617 > HEADER:first-child + DIV > SECTION#firstSection > H1:first-child + DIV > DIV:first-child > SS3-FORCE-FULL-WIDTH:first-child > DIV:first-child > DIV#n2-ss-2-align > DIV:first-child > DIV#n2-ss-2 > DIV:first-child > DIV:first-child > DIV:first-child > DIV:first-child > DIV:first-child + DIV > svg:first-child + DIV + DIV + DIV + DIV > DIV:first-child + DIV > DIV:first-child > DIV:first-child > DIV:first-child > DIV:first-child > DIV:first-child > DIV:first-child > DIV:first-child > DIV:first-child > DIV:first-child + DIV > DIV:first-child > DIV:first-child > P:first-child",
                  "HTML > HEAD:first-child + BODY > MAIN#main > DIV:first-child > DIV#primary > ARTICLE#post-1617 > HEADER:first-child + DIV > SECTION#firstSection > H1:first-child + DIV > DIV:first-child > SS3-FORCE-FULL-WIDTH:first-child > DIV:first-child > DIV#n2-ss-2-align > DIV:first-child > DIV#n2-ss-2 > DIV:first-child > DIV:first-child > DIV:first-child > DIV:first-child > DIV:first-child + DIV > svg:first-child + DIV + DIV + DIV + DIV > DIV:first-child + DIV > DIV:first-child > DIV:first-child > DIV:first-child > DIV:first-child > DIV:first-child > DIV:first-child > DIV:first-child > DIV:first-child > DIV:first-child + DIV > DIV:first-child > DIV:first-child + DIV > P:first-child",
                  "HTML > HEAD:first-child + BODY > MAIN#main > DIV:first-child > DIV#primary > ARTICLE#post-1617 > HEADER:first-child + DIV > SECTION#firstSection > H1:first-child + DIV > DIV:first-child > SS3-FORCE-FULL-WIDTH:first-child > DIV:first-child > DIV#n2-ss-2-align > DIV:first-child > DIV#n2-ss-2 > DIV:first-child > DIV:first-child > DIV:first-child > DIV:first-child > DIV:first-child + DIV > svg:first-child + DIV + DIV + DIV + DIV > DIV:first-child + DIV > DIV:first-child > DIV:first-child > DIV:first-child > DIV:first-child > DIV:first-child > DIV:first-child > DIV:first-child > DIV:first-child > DIV:first-child + DIV > DIV:first-child > DIV:first-child + DIV + DIV > P:first-child"
                ]
              },
              "link_suspicious": {
                "id": "link_suspicious",
                "description": "Suspicious link text",
                "count": 2,
                "selectors": [
                  "HTML > HEAD:first-child + BODY > MAIN#main > DIV:first-child > DIV#primary > ARTICLE#post-1617 > HEADER:first-child + DIV > SECTION:first-child + SECTION + SECTION + SECTION + SECTION > DIV:first-child > H2:first-child + DIV > DIV:first-child > DIV:first-child > DIV:first-child + A + SPAN + SPAN > A:first-child",
                  "HTML > HEAD:first-child + BODY > MAIN#main > DIV:first-child > DIV#primary > ARTICLE#post-1617 > HEADER:first-child + DIV > SECTION:first-child + SECTION + SECTION + SECTION + SECTION > DIV:first-child > H2:first-child + DIV > DIV:first-child > DIV:first-child + DIV > DIV:first-child + A + SPAN + SPAN > A:first-child"
                ]
              },
              "link_redundant": {
                "id": "link_redundant",
                "description": "Redundant link",
                "count": 4,
                "selectors": [
                  "HTML > HEAD:first-child + BODY > DIV#mk-aweb-accessibility-panel-wrapper > DIV#mk-aweb-menu-accessibility-widget > DIV:first-child > SPAN:first-child + I + A",
                  "HTML > HEAD:first-child + BODY > DIV:first-child + STYLE + DIV + NOSCRIPT + HEADER > DIV:first-child > DIV:first-child > DIV:first-child + DIV + NAV > UL#menu-top-menu > LI#menu-item-251 > A:first-child + UL > LI#menu-item-2966 > A:first-child",
                  "HTML > HEAD:first-child + BODY > MAIN#main > DIV:first-child > DIV#primary > ARTICLE#post-1617 > HEADER:first-child + DIV > SECTION:first-child + SECTION + SECTION + SECTION + SECTION > DIV:first-child > H2:first-child + DIV > DIV:first-child > DIV:first-child > DIV:first-child + A + SPAN + SPAN > A:first-child",
                  "HTML > HEAD:first-child + BODY > MAIN#main > DIV:first-child > DIV#primary > ARTICLE#post-1617 > HEADER:first-child + DIV > SECTION:first-child + SECTION + SECTION + SECTION + SECTION > DIV:first-child > H2:first-child + DIV > DIV:first-child > DIV:first-child + DIV > DIV:first-child + A + SPAN + SPAN > A:first-child"
                ]
              },
              "noscript": {
                "id": "noscript",
                "description": "Noscript element",
                "count": 5,
                "selectors": [
                  "HTML > HEAD:first-child + BODY > DIV:first-child + STYLE + DIV + NOSCRIPT",
                  "HTML > HEAD:first-child + BODY > DIV:first-child + STYLE + DIV + NOSCRIPT + HEADER > DIV:first-child + SCRIPT + NOSCRIPT",
                  "HTML > HEAD:first-child + BODY > DIV:first-child + STYLE + DIV + NOSCRIPT + HEADER > DIV:first-child + SCRIPT + NOSCRIPT + SCRIPT + SCRIPT + NOSCRIPT",
                  "HTML > HEAD:first-child + BODY > MAIN#main > DIV:first-child > DIV#primary > ARTICLE#post-1617 > HEADER:first-child + DIV > SECTION#lastSection > DIV:first-child > DIV:first-child + DIV > DIV#wpforms-1678 > FORM#wpforms-form-1678 > NOSCRIPT:first-child",
                  "HTML > HEAD:first-child + BODY > DIV:first-child + STYLE + DIV + NOSCRIPT + HEADER + DIV + MAIN + DIV + FOOTER + SCRIPT + SCRIPT + SCRIPT + SCRIPT + SCRIPT + SCRIPT + SCRIPT + SCRIPT + SCRIPT + SCRIPT + SCRIPT + SCRIPT + SCRIPT + SCRIPT + SCRIPT + SCRIPT + SCRIPT + SCRIPT + SCRIPT + SCRIPT + SCRIPT + SCRIPT + SCRIPT + NOSCRIPT"
                ]
              },
              "tabindex": {
                "id": "tabindex",
                "description": "Tabindex",
                "count": 1,
                "selectors": [
                  "HTML > HEAD:first-child + BODY > DIV#mk-aweb-accessibility-panel-wrapper > A#mk-aweb-open-panel"
                ]
              },
              "text_small": {
                "id": "text_small",
                "description": "Very small text",
                "count": 1,
                "selectors": [
                  "HTML > HEAD:first-child + BODY > MAIN#main > DIV:first-child > DIV#primary > ARTICLE#post-1617 > HEADER:first-child + DIV > SECTION#firstSection > H1:first-child"
                ]
              },
              "youtube_video": {
                "id": "youtube_video",
                "description": "YouTube video",
                "count": 1,
                "selectors": [
                  "HTML > HEAD:first-child + BODY > MAIN#main > DIV:first-child > DIV#primary > ARTICLE#post-1617 > HEADER:first-child + DIV > SECTION:first-child + SECTION > DIV:first-child > DIV:first-child > DIV:first-child + DIV > DIV:first-child > IFRAME:first-child"
                ]
              }
            }
          }
        }
      }
    },
    {
      "type": "score",
      "which": "a11y07",
      "what": "3 packages and 16 custom tests, with duplication discounts",
      "result": {
        "scoreProc": "a11y",
        "version": "7",
        "ruleDiscounts": {
          "axe": {
            "aria-allowed-role": 1,
            "aria-roles": 2,
            "color-contrast": 2,
            "image-redundant-alt": 1,
            "label": 3,
            "link-name": 2,
            "nested-interactive": 2,
            "region": 1
          },
          "ibm": {
            "aria_semantics_role": 2,
            "IBMA_Color_Contrast_WCAG2AA": 2,
            "Rpt_Aria_OrphanedContent_Native_Host_Sematics": 2,
            "Rpt_Aria_ValidIdRef": 2,
            "Rpt_Aria_ValidRole": 2,
            "WCAG20_A_HasText": 2,
            "WCAG20_Fieldset_HasLegend": 3,
            "WCAG20_Input_ExplicitLabel": 2,
            "WCAG20_Input_RadioChkInFieldSet": 3
          },
          "wave": {
            "alt_redundant": 1,
            "aria_reference_broken": 2,
            "contrast": 1,
            "fieldset_missing": 1,
            "label_orphaned": 1,
            "legend_missing": 1,
            "link_empty": 2,
            "select_missing_label": 1
          }
        },
        "rules": {
          "axe": "multiply minor by 2, moderate by 3, serious by 4, critical by 5; sum; subtract discounts",
          "bulk": "subtract 250 from visible elements; make 0 if negative; raise to 0.9th power; multiply by 0.15",
          "embAc": "multiply link- or button-contained links, buttons, inputs, and selects by 3 (discounted)",
          "focAll": "multiply discrepancy between focusable and focused element counts by 3",
          "focInd": "multiply indicatorless-when-focused elements by 5",
          "focOp": "multiply nonfocusable operable elements by 4, nonoperable focusable by 1; sum",
          "hover": "multiply elements changing page on hover by 4, made visible by 2, with directly changed opacity by 0.1, with indirectly changed opacity by 0.2, unhoverable by 2; sum",
          "ibm": "multiply violations by 4, recommendatons by 2; sum; subtract discounts",
          "labClash": "multiply conflictually labeled elements by 2, unlabeled elements by 2; sum",
          "linkUl": "multiply nonunderlined inline links by 3",
          "log": "multiply log items by respective logWeights; sum",
          "menuNav": "multiply Home and End errors by 1 and other key-navigation errors by 3; sum",
          "motion": "get PNG screenshot sizes (sss); get differing-pixel counts between adjacent PNG screenshots (pd); “sssd” = sss difference ÷ smaller sss - 1; multiply mean adjacent sssd by 5, maximum adjacent sssd by 2, maximum over-all ssd by 1; divide mean pd by 10,000, maximum pd by 25,000; multiply count of non-0 pd by 30; sum",
          "radioSet": "multiply radio buttons not in fieldsets with legends and no other-name radio buttons by 2",
          "role": "multiple role attributes with invalid or native-HTML-equivalent values by 2",
          "styleDiff": "for each of element classes block a, inline a, button, h1, h2, h3, h4, h5, and h6, get diffStyles-distinct styles; multiply their count minus 1 by 2; multiply count of elements with non-plurality styles by 0.2; sum",
          "tabNav": "multiply Home and End errors by 1 and other key-navigation errors by 3; sum",
          "wave": "multiply alerts by 2, contrast errors by 3, errors by 4; sum; subtract discounts",
          "zIndex": "multiply non-auto z indexes by 3"
        },
        "diffStyles": [
          "borderStyle",
          "borderWidth",
          "fontStyle",
          "fontWeight",
          "lineHeight",
          "maxHeight",
          "maxWidth",
          "minHeight",
          "minWidth",
          "opacity",
          "outlineOffset",
          "outlineStyle",
          "outlineWidth",
          "textDecorationLine",
          "textDecorationStyle",
          "textDecorationThickness"
        ],
        "logWeights": {
          "count": 0.5,
          "size": 0.01,
          "prohibited": 15,
          "visitTimeout": 10,
          "visitRejection": 10
        },
        "inferences": {},
        "deficit": {
          "total": 737,
          "axe": 31,
          "bulk": 9,
          "embAc": 0,
          "focAll": 6,
          "focInd": 79,
          "focOp": 29,
          "hover": 38,
          "ibm": 56,
          "labClash": 0,
          "linkUl": 39,
          "log": 59,
          "menuNav": 0,
          "motion": 43,
          "radioSet": 0,
          "role": 24,
          "styleDiff": 24,
          "tabNav": 0,
          "wave": 42,
          "zIndex": 258
        }
      }
    }
  ],
  "testTimes": [
    [
      "hover",
      55
    ],
    [
      "motion",
      14
    ],
    [
      "ibm",
      14
    ],
    [
      "wave",
      5
    ],
    [
      "axe",
      1
    ],
    [
      "focAll",
      1
    ],
    [
      "bulk",
      0
    ],
    [
      "embAc",
      0
    ],
    [
      "focInd",
      0
    ],
    [
      "focOp",
      0
    ],
    [
      "labClash",
      0
    ],
    [
      "linkUl",
      0
    ],
    [
      "menuNav",
      0
    ],
    [
      "radioSet",
      0
    ],
    [
      "role",
      0
    ],
    [
      "styleDiff",
      0
    ],
    [
      "tabNav",
      0
    ],
    [
      "zIndex",
      0
    ]
  ]
}